processor_tools/__init__.py
processor_tools/_version.py
processor_tools/config_io.py
processor_tools/context.py
processor_tools/init_config_cli.py
processor_tools/processor.py
processor_tools/setup_utils.py
processor_tools/utils/__init__.py
processor_tools/utils/dict_tools.py
processor_tools/utils/formatters.py
processor_tools-0.2.1.dist-info/METADATA
processor_tools-0.2.1.dist-info/WHEEL
processor_tools-0.2.1.dist-info/top_level.txt
processor_tools-0.2.1.dist-info/RECORD
